browser_use/README.md
browser_use/__init__.py
browser_use/logging_config.py
browser_use/utils.py
browser_use/agent/prompts.py
browser_use/agent/service.py
browser_use/agent/tests.py
browser_use/agent/views.py
browser_use/agent/message_manager/service.py
browser_use/agent/message_manager/tests.py
browser_use/agent/message_manager/views.py
browser_use/browser/service.py
browser_use/browser/views.py
browser_use/browser/tests/screenshot_test.py
browser_use/browser/tests/test_clicks.py
browser_use/controller/service.py
browser_use/controller/views.py
browser_use/controller/registry/service.py
browser_use/controller/registry/views.py
browser_use/controller/tests/current_state.py
browser_use/dom/__init__.py
browser_use/dom/buildDomTree.js
browser_use/dom/history_tree_processor.py
browser_use/dom/service.py
browser_use/dom/views.py
browser_use/dom/tests/extraction_test.py
browser_use/dom/tests/process_dom_test.py
browser_use/telemetry/service.py
browser_use/telemetry/views.py
browser_use_enhanced-0.1.20.dist-info/METADATA
browser_use_enhanced-0.1.20.dist-info/WHEEL
browser_use_enhanced-0.1.20.dist-info/licenses/LICENSE
browser_use_enhanced-0.1.20.dist-info/RECORD
