Metadata-Version: 2.3
Name: browser-use-enhanced
Version: 0.1.20
Summary: Make websites accessible for AI agents
Requires-Python: <3.12,>=3.11
Requires-Dist: beautifulsoup4>=4.12.3
Requires-Dist: google-generativeai
Requires-Dist: httpx==0.27.2
Requires-Dist: langchain-anthropic>=0.3.0
Requires-Dist: langchain-fireworks>=0.2.5
Requires-Dist: langchain-google-genai>=0.1.0
Requires-Dist: langchain-openai>=0.2.10
Requires-Dist: langchain>=0.3.9
Requires-Dist: maincontentextractor>=0.0.4
Requires-Dist: playwright>=1.49.0
Requires-Dist: posthog>=3.7.4
Requires-Dist: pydantic>=2.10.2
Requires-Dist: python-dotenv>=1.0.1
Requires-Dist: requests>=2.32.3
Provides-Extra: dev
Requires-Dist: build>=1.2.2; extra == 'dev'
Requires-Dist: pytest-asyncio>=0.24.0; extra == 'dev'
Requires-Dist: pytest>=8.3.3; extra == 'dev'
Requires-Dist: twine>=4.0.2; extra == 'dev'
